aiocoap/__init__.py
aiocoap/blockwise.py
aiocoap/credentials.py
aiocoap/defaults.py
aiocoap/edhoc.py
aiocoap/error.py
aiocoap/interfaces.py
aiocoap/message.py
aiocoap/messagemanager.py
aiocoap/meta.py
aiocoap/options.py
aiocoap/optiontypes.py
aiocoap/oscore.py
aiocoap/oscore_sitewrapper.py
aiocoap/pipe.py
aiocoap/protocol.py
aiocoap/resource.py
aiocoap/tokenmanager.py
aiocoap/cli/__init__.py
aiocoap/cli/client.py
aiocoap/cli/common.py
aiocoap/cli/defaults.py
aiocoap/cli/fileserver.py
aiocoap/cli/keygen.py
aiocoap/cli/proxy.py
aiocoap/cli/rd.py
aiocoap/numbers/__init__.py
aiocoap/numbers/codes.py
aiocoap/numbers/constants.py
aiocoap/numbers/contentformat.py
aiocoap/numbers/optionnumbers.py
aiocoap/numbers/types.py
aiocoap/proxy/__init__.py
aiocoap/proxy/client.py
aiocoap/proxy/server.py
aiocoap/resourcedirectory/__init__.py
aiocoap/resourcedirectory/client/__init__.py
aiocoap/resourcedirectory/client/register.py
aiocoap/transports/__init__.py
aiocoap/transports/generic_udp.py
aiocoap/transports/oscore.py
aiocoap/transports/rfc8323common.py
aiocoap/transports/simple6.py
aiocoap/transports/simplesocketserver.py
aiocoap/transports/tcp.py
aiocoap/transports/tinydtls.py
aiocoap/transports/tinydtls_server.py
aiocoap/transports/tls.py
aiocoap/transports/udp6.py
aiocoap/transports/ws.py
aiocoap/util/__init__.py
aiocoap/util/cli.py
aiocoap/util/contenttype.py
aiocoap/util/cryptography_additions.py
aiocoap/util/linkformat.py
aiocoap/util/linkformat_pygments.py
aiocoap/util/prettyprint.py
aiocoap/util/pyodide_websockets.py
aiocoap/util/socknumbers.py
aiocoap/util/uri.py
aiocoap/util/asyncio/__init__.py
aiocoap/util/asyncio/getaddrinfo_addrconfig.py
aiocoap/util/asyncio/recvmsg.py
aiocoap/util/asyncio/timeoutdict.py
aiocoap/util/vendored/link_header.py
aiocoap-0.4.13.dist-info/METADATA
aiocoap-0.4.13.dist-info/WHEEL
aiocoap-0.4.13.dist-info/entry_points.txt
aiocoap-0.4.13.dist-info/top_level.txt
aiocoap-0.4.13.dist-info/RECORD
