Metadata-Version: 2.2
Name: aiocoap
Version: 0.4.13
Summary: Python CoAP library
Author: the aiocoap contributors
Author-email: Christian Amsüss <chrysn@fsfe.org>
License: MIT
Project-URL: homepage, https://christian.amsuess.com/tools/aiocoap/
Project-URL: repository, https://codeberg.org/aiocoap/aiocoap
Project-URL: documentation, https://aiocoap.readthedocs.org/
Project-URL: changelog, https://codeberg.org/aiocoap/aiocoap/src/branch/main/NEWS.rst
Keywords: coap,asyncio,iot
Classifier: Development Status :: 5 - Production/Stable
Classifier: Framework :: AsyncIO
Classifier: Intended Audience :: Developers
Classifier: License :: OSI Approved :: MIT License
Classifier: Operating System :: OS Independent
Classifier: Programming Language :: Python
Classifier: Programming Language :: Python :: 3
Classifier: Topic :: Internet
Classifier: Topic :: Security
Classifier: Topic :: Software Development :: Libraries :: Python Modules
Classifier: Topic :: System :: Networking
Requires-Python: >=3.10
Provides-Extra: linkheader
Provides-Extra: oscore
Requires-Dist: cbor2; extra == "oscore"
Requires-Dist: cryptography>=2.5; extra == "oscore"
Requires-Dist: filelock; extra == "oscore"
Requires-Dist: ge25519; extra == "oscore"
Requires-Dist: lakers-python<0.6,>=0.5; extra == "oscore"
Provides-Extra: tinydtls
Requires-Dist: DTLSSocket>=0.1.18; extra == "tinydtls"
Provides-Extra: ws
Requires-Dist: websockets<14,>=13; extra == "ws"
Provides-Extra: prettyprint
Requires-Dist: cbor2; extra == "prettyprint"
Requires-Dist: pygments>=2.1; extra == "prettyprint"
Requires-Dist: cbor-diag; extra == "prettyprint"
Provides-Extra: docs
Requires-Dist: sphinx>=5; extra == "docs"
Requires-Dist: sphinx-argparse; extra == "docs"
Provides-Extra: all
Requires-Dist: cbor2; extra == "all"
Requires-Dist: cryptography>=2.5; extra == "all"
Requires-Dist: filelock; extra == "all"
Requires-Dist: ge25519; extra == "all"
Requires-Dist: lakers-python<0.6,>=0.5; extra == "all"
Requires-Dist: DTLSSocket>=0.1.18; extra == "all"
Requires-Dist: websockets<14,>=13; extra == "all"
Requires-Dist: cbor2; extra == "all"
Requires-Dist: pygments; extra == "all"
Requires-Dist: cbor-diag; extra == "all"
